nerdd_module/__init__.py
nerdd_module/cli.py
nerdd_module/problem.py
nerdd_module/py.typed
nerdd_module/version.py
nerdd_module/config/__init__.py
nerdd_module/config/configuration.py
nerdd_module/config/default_configuration.py
nerdd_module/config/dict_configuration.py
nerdd_module/config/merged_configuration.py
nerdd_module/config/models.py
nerdd_module/config/package_configuration.py
nerdd_module/config/search_yaml_configuration.py
nerdd_module/config/yaml_configuration.py
nerdd_module/converters/__init__.py
nerdd_module/converters/basic_type_converter.py
nerdd_module/converters/converter.py
nerdd_module/converters/converter_config.py
nerdd_module/converters/mol_converter.py
nerdd_module/converters/problem_list_converter.py
nerdd_module/converters/representation_converter.py
nerdd_module/converters/source_list_converter.py
nerdd_module/converters/void_converter.py
nerdd_module/input/__init__.py
nerdd_module/input/depth_first_explorer.py
nerdd_module/input/explorer.py
nerdd_module/input/file_reader.py
nerdd_module/input/gzip_reader.py
nerdd_module/input/inchi_reader.py
nerdd_module/input/list_reader.py
nerdd_module/input/mol_reader.py
nerdd_module/input/reader.py
nerdd_module/input/reader_config.py
nerdd_module/input/sdf_reader.py
nerdd_module/input/smiles_reader.py
nerdd_module/input/stream_reader.py
nerdd_module/input/string_reader.py
nerdd_module/input/tar_reader.py
nerdd_module/input/zip_reader.py
nerdd_module/model/__init__.py
nerdd_module/model/assign_name_step.py
nerdd_module/model/convert_representations_step.py
nerdd_module/model/enforce_schema_step.py
nerdd_module/model/model.py
nerdd_module/model/prediction_step.py
nerdd_module/model/read_input_step.py
nerdd_module/model/write_output_step.py
nerdd_module/output/__init__.py
nerdd_module/output/csv_writer.py
nerdd_module/output/file_writer.py
nerdd_module/output/iterator_writer.py
nerdd_module/output/pandas_writer.py
nerdd_module/output/record_list_writer.py
nerdd_module/output/sdf_writer.py
nerdd_module-0.3.51.dist-info/licenses/LICENSE
nerdd_module-0.3.51.dist-info/METADATA
nerdd_module-0.3.51.dist-info/WHEEL
nerdd_module-0.3.51.dist-info/top_level.txt
nerdd_module-0.3.51.dist-info/RECORD
